Metadata-Version: 2.1
Name: kaan_trial2
Version: 0.0.1
Requires-Python: >=3.9
Requires-Dist: google-cloud-storage
Requires-Dist: cloudevents
Requires-Dist: google-cloud-logging
Requires-Dist: google-auth
Requires-Dist: google-auth-oauthlib
Requires-Dist: google-cloud-pubsub
Requires-Dist: google-cloud-secret-manager
Provides-Extra: dev
Requires-Dist: pytest; extra == "dev"
Requires-Dist: pytest-mock; extra == "dev"
